Elevator.v
module ElevatorController(
    input clk, reset,
    input [3:0] floor_btn,      // internal floor request buttons (4 floors)
    input [3:0] call_btn,       // external call buttons (4 floors)
    input overload,
    input door_closed,
    output reg move_up,
    output reg move_down,
    output reg open_door,
    output reg busy,
    output reg [1:0] current_floor
);

    // FSM state parameters
    parameter IDLE               = 3'b000,
              MOVING_UP          = 3'b001,
              MOVING_DOWN        = 3'b010,
              OPEN_DOOR          = 3'b011,
              WAIT_FOR_DOOR_CLOSE= 3'b100,
              OVERLOAD_STATE     = 3'b101;

    reg [2:0] state, next_state;
    reg [3:0] requests;
    reg [1:0] target_floor; // New: stores priority-selected next floor

    // Combine all floor and call requests
    always @(*) begin
        requests = floor_btn | call_btn;
    end

    // Priority floor selection
    always @(*) begin
        // Priority encoder: lowest numbered floor first
        if (requests[0])
            target_floor = 2'd0;
        else if (requests[1])
            target_floor = 2'd1;
        else if (requests[2])
            target_floor = 2'd2;
        else if (requests[3])
            target_floor = 2'd3;
        else
            target_floor = current_floor;
    end

    // State transition logic
    always @(posedge clk or posedge reset) begin
        if (reset) begin
            state <= IDLE;
            current_floor <= 2'd0;
        end else begin
            state <= next_state;
        end
    end

    // FSM logic
    always @(*) begin
        // Default outputs
        move_up = 0;
        move_down = 0;
        open_door = 0;
        busy = 1;
        next_state = state;

        case (state)
            IDLE: begin
                busy = 0;
                if (overload)
                    next_state = OVERLOAD_STATE;
                else if (requests[current_floor])
                    next_state = OPEN_DOOR;
                else if (|requests) begin
                    if (target_floor > current_floor)
                        next_state = MOVING_UP;
                    else if (target_floor < current_floor)
                        next_state = MOVING_DOWN;
                end
            end

            MOVING_UP: begin
                move_up = 1;
                if (current_floor < 3)
                    next_state = OPEN_DOOR;
            end

            MOVING_DOWN: begin
                move_down = 1;
                if (current_floor > 0)
                    next_state = OPEN_DOOR;
            end

            OPEN_DOOR: begin
                open_door = 1;
                next_state = WAIT_FOR_DOOR_CLOSE;
            end

            WAIT_FOR_DOOR_CLOSE: begin
                if (overload)
                    next_state = OVERLOAD_STATE;
                else if (door_closed)
                    next_state = IDLE;
            end

            OVERLOAD_STATE: begin
                open_door = 1;
                if (!overload && door_closed)
                    next_state = IDLE;
            end
        endcase
    end

    // Floor counter logic
    always @(posedge clk or posedge reset) begin
        if (reset)
            current_floor <= 0;
        else if (move_up && current_floor < 3)
            current_floor <= current_floor + 1;
        else if (move_down && current_floor > 0)
            current_floor <= current_floor - 1;
    end
endmodule

Elevator_TB.v
module tb_ElevatorController;

// Inputs
reg clk = 0;
reg reset;
reg [3:0] floor_btn;
reg [3:0] call_btn;
reg overload;
reg door_closed;

// Outputs
wire move_up;
wire move_down;
wire open_door;
wire busy;
wire [1:0] current_floor;

// Instantiate the Unit Under Test (UUT)
ElevatorController uut (
    .clk(clk),
    .reset(reset),
    .floor_btn(floor_btn),
    .call_btn(call_btn),
    .overload(overload),
    .door_closed(door_closed),
    .move_up(move_up),
    .move_down(move_down),
    .open_door(open_door),
    .busy(busy),
    .current_floor(current_floor)
);

// Clock generation
always #5 clk = ~clk; // 10 time units clock period

initial begin
    // GTKWave dump
    $dumpfile("elevator.vcd");
    $dumpvars(0, tb_ElevatorController);

    // Initial states
    reset = 1;
    floor_btn = 4'b0000;
    call_btn = 4'b0000;
    overload = 0;
    door_closed = 1;

    #10 reset = 0;

    // Scenario 1: Call from floor 3
    #10 call_btn = 4'b1000; // floor 3
    #20 call_btn = 4'b0000;

    #60;

    // Scenario 2: Call from floor 1
    #10 call_btn = 4'b0010;
    #20 call_btn = 4'b0000;

    #60;

    // Scenario 3: Internal button press for floor 0
    #10 floor_btn = 4'b0001;
    #20 floor_btn = 4'b0000;

    #80;

    // Scenario 4: Simulate overload while door open
    #10 overload = 1;
    #20 overload = 0;

    // Door closes after overload clears
    #10 door_closed = 0;
    #20 door_closed = 1;

    #100;
    $finish;
end

endmodule

elevator.vcd
$date
	Tue Jul 15 22:34:05 2025
$end
$version
	Icarus Verilog
$end
$timescale
	1s
$end
$scope module tb_ElevatorController $end
$var wire 1 ! open_door $end
$var wire 1 " move_up $end
$var wire 1 # move_down $end
$var wire 2 $ current_floor [1:0] $end
$var wire 1 % busy $end
$var reg 4 & call_btn [3:0] $end
$var reg 1 ' clk $end
$var reg 1 ( door_closed $end
$var reg 4 ) floor_btn [3:0] $end
$var reg 1 * overload $end
$var reg 1 + reset $end
$scope module uut $end
$var wire 4 , call_btn [3:0] $end
$var wire 1 ' clk $end
$var wire 1 ( door_closed $end
$var wire 4 - floor_btn [3:0] $end
$var wire 1 * overload $end
$var wire 1 + reset $end
$var parameter 3 . IDLE $end
$var parameter 3 / MOVING_DOWN $end
$var parameter 3 0 MOVING_UP $end
$var parameter 3 1 OPEN_DOOR $end
$var parameter 3 2 OVERLOAD_STATE $end
$var parameter 3 3 WAIT_FOR_DOOR_CLOSE $end
$var reg 1 % busy $end
$var reg 2 4 current_floor [1:0] $end
$var reg 1 # move_down $end
$var reg 1 " move_up $end
$var reg 3 5 next_state [2:0] $end
$var reg 1 ! open_door $end
$var reg 4 6 requests [3:0] $end
$var reg 3 7 state [2:0] $end
$var reg 2 8 target_floor [1:0] $end
$upscope $end
$upscope $end
$enddefinitions $end
$comment Show the parameter values. $end
$dumpall
b100 3
b101 2
b11 1
b1 0
b10 /
b0 .
$end
#0
$dumpvars
b0 8
b0 7
b0 6
b0 5
b0 4
b0 -
b0 ,
1+
0*
b0 )
1(
0'
b0 &
0%
b0 $
0#
0"
0!
$end
#5
1'
#10
0'
0+
#15
1'
#20
b1 5
0%
b11 8
b1000 6
0'
b1000 &
b1000 ,
#25
b11 5
1"
1%
b1 7
1'
#30
0'
#35
b100 5
1!
0"
b11 7
b1 $
b1 4
1'
#40
b100 5
1!
b1 8
b0 6
0'
b0 &
b0 ,
#45
b0 5
0!
b100 7
1'
#50
0'
#55
0%
b0 7
1'
#60
0'
#65
1'
#70
0'
#75
1'
#80
0'
#85
1'
#90
0'
#95
1'
#100
0'
#105
1'
#110
b11 5
0%
b10 6
0'
b10 &
b10 ,
#115
b100 5
1!
1%
b11 7
1'
#120
0'
#125
b0 5
0!
b100 7
1'
#130
b0 5
b0 6
0'
b0 &
b0 ,
#135
0%
b0 7
1'
#140
0'
#145
1'
#150
0'
#155
1'
#160
0'
#165
1'
#170
0'
#175
1'
#180
0'
#185
1'
#190
0'
#195
1'
#200
b10 5
0%
b0 8
b1 6
0'
b1 )
b1 -
#205
b11 5
1#
1%
b10 7
1'
#210
0'
#215
b100 5
1!
0#
b11 7
b0 $
b0 4
1'
#220
b100 5
1!
b0 6
0'
b0 )
b0 -
#225
b0 5
0!
b100 7
1'
#230
0'
#235
0%
b0 7
1'
#240
0'
#245
1'
#250
0'
#255
1'
#260
0'
#265
1'
#270
0'
#275
1'
#280
0'
#285
1'
#290
0'
#295
1'
#300
0'
#305
1'
#310
b101 5
0%
0'
1*
#315
1!
1%
b101 7
1'
#320
0'
#325
1'
#330
b0 5
1!
0'
0*
#335
0%
0!
b0 7
1'
#340
0%
0'
0(
#345
1'
#350
0'
#355
1'
#360
0%
0'
1(
